tidyviz/__init__.py
tidyviz/tidy/__init__.py
tidyviz/tidy/reshape.py
tidyviz/tidy/validate.py
tidyviz/viz/__init__.py
tidyviz/viz/categorical.py
tidyviz/viz/themes.py
tidyviz-0.1.0.dist-info/licenses/LICENSE
tidyviz-0.1.0.dist-info/METADATA
tidyviz-0.1.0.dist-info/WHEEL
tidyviz-0.1.0.dist-info/top_level.txt
tidyviz-0.1.0.dist-info/RECORD
