Metadata-Version: 2.4
Name: tidyviz
Version: 0.1.0
Summary: A Python package for tidying and visualizing survey data
Author-email: Pingfan Hu <pingfan0727@gmail.com>
License-Expression: MIT
Project-URL: Homepage, https://github.com/pingfan-hu/tidyviz
Project-URL: Documentation, https://github.com/pingfan-hu/tidyviz#readme
Project-URL: Repository, https://github.com/pingfan-hu/tidyviz
Project-URL: Bug Tracker, https://github.com/pingfan-hu/tidyviz/issues
Keywords: survey,data-cleaning,data-visualization,research,analytics
Classifier: Development Status :: 3 - Alpha
Classifier: Intended Audience :: Science/Research
Classifier: Programming Language :: Python :: 3
Classifier: Programming Language :: Python :: 3.8
Classifier: Programming Language :: Python :: 3.9
Classifier: Programming Language :: Python :: 3.10
Classifier: Programming Language :: Python :: 3.11
Classifier: Topic :: Scientific/Engineering :: Information Analysis
Requires-Python: >=3.8
License-File: LICENSE
Requires-Dist: pandas>=1.3.0
Requires-Dist: numpy>=1.20.0
Requires-Dist: matplotlib>=3.4.0
Requires-Dist: seaborn>=0.11.0
Provides-Extra: dev
Requires-Dist: pytest>=7.0.0; extra == "dev"
Requires-Dist: pytest-cov>=3.0.0; extra == "dev"
Requires-Dist: black>=22.0.0; extra == "dev"
Requires-Dist: flake8>=4.0.0; extra == "dev"
Dynamic: license-file
